<?xml version="1.0" encoding="utf-8"?>
<annotation verified="no">
  <folder>data</folder>
  <filename>476</filename>
  <path>F:\618newnew\BackEnd\sanxiang2021_3\bin\Debug\netcoreapp3.1\Users\VisionMaker\VisionSoft\data\JPEGImages\476.jpg</path>
  <source>
    <database>Unknown</database>
  </source>
  <size>
    <width>1280</width>
    <height>720</height>
    <depth>3</depth>
  </size>
  <segmented>0</segmented>
  <object>
    <name>XLabel</name>
    <pose>Unspecified</pose>
    <truncated>0</truncated>
    <Difficult>0</Difficult>
    <bndbox>
      <xmin>770</xmin>
      <ymin>486</ymin>
      <xmax>812</xmax>
      <ymax>524</ymax>
    </bndbox>
  </object>
  <object>
    <name>YLabel</name>
    <pose>Unspecified</pose>
    <truncated>0</truncated>
    <Difficult>0</Difficult>
    <bndbox>
      <xmin>528</xmin>
      <ymin>482</ymin>
      <xmax>575</xmax>
      <ymax>523</ymax>
    </bndbox>
  </object>
  <object>
    <name>none</name>
    <pose>Unspecified</pose>
    <truncated>0</truncated>
    <Difficult>0</Difficult>
    <bndbox>
      <xmin>706</xmin>
      <ymin>278</ymin>
      <xmax>875</xmax>
      <ymax>445</ymax>
    </bndbox>
  </object>
  <object>
    <name>withoutcover</name>
    <pose>Unspecified</pose>
    <truncated>0</truncated>
    <Difficult>0</Difficult>
    <bndbox>
      <xmin>450</xmin>
      <ymin>253</ymin>
      <xmax>639</xmax>
      <ymax>444</ymax>
    </bndbox>
  </object>
</annotation>