<?xml version="1.0" encoding="utf-8"?>
<annotation verified="no">
  <folder>data</folder>
  <filename>470</filename>
  <path>F:\618newnew\BackEnd\sanxiang2021_3\bin\Debug\netcoreapp3.1\Users\VisionMaker\VisionSoft\data\JPEGImages\470.jpg</path>
  <source>
    <database>Unknown</database>
  </source>
  <size>
    <width>1280</width>
    <height>720</height>
    <depth>3</depth>
  </size>
  <segmented>0</segmented>
  <object>
    <name>XLabel</name>
    <pose>Unspecified</pose>
    <truncated>0</truncated>
    <Difficult>0</Difficult>
    <bndbox>
      <xmin>579</xmin>
      <ymin>509</ymin>
      <xmax>631</xmax>
      <ymax>554</ymax>
    </bndbox>
  </object>
  <object>
    <name>YLabel</name>
    <pose>Unspecified</pose>
    <truncated>0</truncated>
    <Difficult>0</Difficult>
    <bndbox>
      <xmin>310</xmin>
      <ymin>513</ymin>
      <xmax>362</xmax>
      <ymax>563</ymax>
    </bndbox>
  </object>
  <object>
    <name>transparenexcept</name>
    <pose>Unspecified</pose>
    <truncated>0</truncated>
    <Difficult>0</Difficult>
    <bndbox>
      <xmin>501</xmin>
      <ymin>265</ymin>
      <xmax>752</xmax>
      <ymax>518</ymax>
    </bndbox>
  </object>
  <object>
    <name>withoutcover</name>
    <pose>Unspecified</pose>
    <truncated>0</truncated>
    <Difficult>0</Difficult>
    <bndbox>
      <xmin>117</xmin>
      <ymin>277</ymin>
      <xmax>427</xmax>
      <ymax>508</ymax>
    </bndbox>
  </object>
</annotation>